kglib/__init__.py
kglib/kgcn/__init__.py
kglib/kgcn/core/__init__.py
kglib/kgcn/core/model.py
kglib/kgcn/core/model_test.py
kglib/kgcn/core/ingest/__init__.py
kglib/kgcn/core/ingest/encode/__init__.py
kglib/kgcn/core/ingest/encode/boolean.py
kglib/kgcn/core/ingest/encode/boolean_test.py
kglib/kgcn/core/ingest/encode/encode.py
kglib/kgcn/core/ingest/encode/encode_test.py
kglib/kgcn/core/ingest/encode/schema.py
kglib/kgcn/core/ingest/encode/schema_test.py
kglib/kgcn/core/ingest/encode/tf_hub.py
kglib/kgcn/core/ingest/encode/tf_hub_test.py
kglib/kgcn/core/ingest/preprocess/__init__.py
kglib/kgcn/core/ingest/preprocess/persistence.py
kglib/kgcn/core/ingest/preprocess/preprocess.py
kglib/kgcn/core/ingest/traverse/__init__.py
kglib/kgcn/core/ingest/traverse/data/__init__.py
kglib/kgcn/core/ingest/traverse/data/context/__init__.py
kglib/kgcn/core/ingest/traverse/data/context/array.py
kglib/kgcn/core/ingest/traverse/data/context/array_IT.py
kglib/kgcn/core/ingest/traverse/data/context/array_test.py
kglib/kgcn/core/ingest/traverse/data/context/builder.py
kglib/kgcn/core/ingest/traverse/data/context/builder_IT.py
kglib/kgcn/core/ingest/traverse/data/context/builder_mocks.py
kglib/kgcn/core/ingest/traverse/data/context/builder_test.py
kglib/kgcn/core/ingest/traverse/data/context/neighbour.py
kglib/kgcn/core/ingest/traverse/data/context/neighbour_test.py
kglib/kgcn/core/ingest/traverse/data/context/utils.py
kglib/kgcn/core/ingest/traverse/data/sample/__init__.py
kglib/kgcn/core/ingest/traverse/data/sample/ordered.py
kglib/kgcn/core/ingest/traverse/data/sample/ordered_test.py
kglib/kgcn/core/ingest/traverse/data/sample/random_sampling.py
kglib/kgcn/core/ingest/traverse/data/sample/random_sampling_test.py
kglib/kgcn/core/ingest/traverse/data/sample/sample.py
kglib/kgcn/core/ingest/traverse/schema/__init__.py
kglib/kgcn/core/ingest/traverse/schema/executor.py
kglib/kgcn/core/ingest/traverse/schema/traversal.py
kglib/kgcn/core/ingest/traverse/schema/traversal_test.py
grakn_kglib-0.1.dist-info/METADATA
grakn_kglib-0.1.dist-info/WHEEL
grakn_kglib-0.1.dist-info/top_level.txt
grakn_kglib-0.1.dist-info/RECORD
